flask_sitemapper/__init__.py
flask_sitemapper/gzip.py
flask_sitemapper/sitemapper.py
flask_sitemapper/templates.py
flask_sitemapper/url.py
flask_sitemapper-1.8.2.dist-info/LICENSE
flask_sitemapper-1.8.2.dist-info/METADATA
flask_sitemapper-1.8.2.dist-info/WHEEL
flask_sitemapper-1.8.2.dist-info/RECORD
