Metadata-Version: 2.1
Name: flask-sitemapper
Version: 1.8.2
Summary: Flask extension for generating XML sitemaps
Home-page: https://github.com/h-janes/flask-sitemapper
License: MIT
Keywords: python3,flask,sitemap,xml
Author: h-janes
Author-email: dev@hjanes.com
Requires-Python: >=3.8
Classifier: Framework :: Flask
Classifier: License :: OSI Approved :: MIT License
Classifier: Operating System :: OS Independent
Classifier: Programming Language :: Python :: 3
Classifier: Programming Language :: Python :: 3.8
Classifier: Programming Language :: Python :: 3.9
Classifier: Programming Language :: Python :: 3.10
Classifier: Programming Language :: Python :: 3.11
Classifier: Programming Language :: Python :: 3.12
Classifier: Programming Language :: Python :: 3.13
Requires-Dist: flask (>=2.2.2)
Requires-Dist: jinja2 (>=3.1.3)
Project-URL: Documentation, https://github.com/h-janes/flask-sitemapper/wiki
Project-URL: Repository, https://github.com/h-janes/flask-sitemapper
